Metadata-Version: 1.0
Name: dfpvizpy
Version: 0.1
Summary: Data for Progress Viz Styling in Python
Home-page: UNKNOWN
Author: Data For Progress
Author-email: UNKNOWN
License: MIT
Platform: UNKNOWN
